PyHyperScattering/ALS11012RSoXSLoader.py
PyHyperScattering/CMSGIWAXSLoader.py
PyHyperScattering/ESRFID2Loader.py
PyHyperScattering/FileIO.py
PyHyperScattering/FileLoader.py
PyHyperScattering/Fitting.py
PyHyperScattering/HDR.py
PyHyperScattering/IntegrationUtils.py
PyHyperScattering/Nexus.py
PyHyperScattering/PFEnergySeriesIntegrator.py
PyHyperScattering/PFGeneralIntegrator.py
PyHyperScattering/PGGeneralIntegrator.py
PyHyperScattering/PlotTools.py
PyHyperScattering/RSoXS.py
PyHyperScattering/SMIRSoXSLoader.py
PyHyperScattering/SST1RSoXSDB.py
PyHyperScattering/SST1RSoXSLoader.py
PyHyperScattering/WPIntegrator.py
PyHyperScattering/__init__.py
PyHyperScattering/_version.py
PyHyperScattering/cyrsoxsLoader.py
PyHyperScattering/integrate.py
PyHyperScattering/load.py
PyHyperScattering/util.py
pyhyperscattering-0.2.10.dist-info/licenses/LICENSE
pyhyperscattering-0.2.10.dist-info/METADATA
pyhyperscattering-0.2.10.dist-info/WHEEL
pyhyperscattering-0.2.10.dist-info/top_level.txt
pyhyperscattering-0.2.10.dist-info/RECORD
