Metadata-Version: 2.4
Name: PyHyperScattering
Version: 0.2.10
Summary: Utilities for loading, reducing, fitting, and plotting hyperspectral x-ray and neutron scattering data.
Author-email: Peter Beaucage <peter.beaucage@nist.gov>
License-Expression: NIST-PD-fallback
Project-URL: Homepage, https://github.com/usnistgov/pyhyperscattering
Project-URL: Bug Tracker, https://github.com/usnistgov/pyhyperscattering/issues
Project-URL: Project Site, https://www.nist.gov/laboratories/tools-instruments/polarized-resonant-soft-x-ray-scattering-p-rsoxs
Classifier: Programming Language :: Python :: 3
Classifier: Operating System :: OS Independent
Classifier: Development Status :: 3 - Alpha
Classifier: Intended Audience :: Science/Research
Classifier: Topic :: Scientific/Engineering :: Chemistry
Classifier: Topic :: Scientific/Engineering :: Physics
Requires-Python: >=3.6
License-File: LICENSE
Requires-Dist: h5py
Requires-Dist: numpy
Requires-Dist: pandas
Requires-Dist: pyfai
Requires-Dist: scikit-image
Requires-Dist: scipy
Requires-Dist: pillow
Requires-Dist: xarray
Requires-Dist: bottleneck
Requires-Dist: tqdm
Requires-Dist: astropy
Requires-Dist: fabio
Requires-Dist: pydata_sphinx_theme
Requires-Dist: numexpr!=2.8.5,!=2.8.6
Provides-Extra: grazing
Requires-Dist: silx==2.0.0; extra == "grazing"
Requires-Dist: pygix; extra == "grazing"
Provides-Extra: bluesky
Requires-Dist: tiled[client]>=0.1.0a74; extra == "bluesky"
Requires-Dist: bluesky-tiled-plugins; extra == "bluesky"
Provides-Extra: performance
Requires-Dist: pyopencl; extra == "performance"
Requires-Dist: dask; extra == "performance"
Requires-Dist: cupy; extra == "performance"
Provides-Extra: ui
Requires-Dist: holoviews; extra == "ui"
Requires-Dist: hvplot; extra == "ui"
Requires-Dist: ipyaggrid; extra == "ui"
Requires-Dist: matplotlib; extra == "ui"
Provides-Extra: doc
Requires-Dist: sphinx; extra == "doc"
Requires-Dist: pydata_sphinx_theme; extra == "doc"
Provides-Extra: dev
Requires-Dist: flake8; extra == "dev"
Requires-Dist: pytest; extra == "dev"
Requires-Dist: coverage; extra == "dev"
Requires-Dist: pybind11; extra == "dev"
Requires-Dist: wheel; extra == "dev"
Provides-Extra: test
Requires-Dist: pytest; extra == "test"
Requires-Dist: black; extra == "test"
Requires-Dist: codecov; extra == "test"
Requires-Dist: pylint; extra == "test"
Provides-Extra: all-nogpu
Requires-Dist: tiled[client]>=0.1.0a74; extra == "all-nogpu"
Requires-Dist: bluesky-tiled-plugins; extra == "all-nogpu"
Requires-Dist: pyopencl; extra == "all-nogpu"
Requires-Dist: dask; extra == "all-nogpu"
Requires-Dist: holoviews; extra == "all-nogpu"
Requires-Dist: hvplot; extra == "all-nogpu"
Requires-Dist: sphinx; extra == "all-nogpu"
Requires-Dist: pydata_sphinx_theme; extra == "all-nogpu"
Requires-Dist: pytest; extra == "all-nogpu"
Requires-Dist: black; extra == "all-nogpu"
Requires-Dist: codecov; extra == "all-nogpu"
Requires-Dist: pylint; extra == "all-nogpu"
Requires-Dist: flake8; extra == "all-nogpu"
Requires-Dist: pytest; extra == "all-nogpu"
Requires-Dist: coverage; extra == "all-nogpu"
Requires-Dist: pybind11; extra == "all-nogpu"
Requires-Dist: wheel; extra == "all-nogpu"
Provides-Extra: all
Requires-Dist: tiled[client]>=0.1.0a74; extra == "all"
Requires-Dist: bluesky-tiled-plugins; extra == "all"
Requires-Dist: pygix; extra == "all"
Requires-Dist: pyopencl; extra == "all"
Requires-Dist: dask; extra == "all"
Requires-Dist: cupy; extra == "all"
Requires-Dist: holoviews; extra == "all"
Requires-Dist: hvplot; extra == "all"
Requires-Dist: silx==2.0.0; extra == "all"
Requires-Dist: sphinx; extra == "all"
Requires-Dist: pydata_sphinx_theme; extra == "all"
Requires-Dist: pytest; extra == "all"
Requires-Dist: black; extra == "all"
Requires-Dist: codecov; extra == "all"
Requires-Dist: pylint; extra == "all"
Requires-Dist: flake8; extra == "all"
Requires-Dist: pytest; extra == "all"
Requires-Dist: coverage; extra == "all"
Requires-Dist: pybind11; extra == "all"
Requires-Dist: wheel; extra == "all"
Dynamic: license-file
